{
    "perguntas":[
        {
            "pergunta": "Pergunta 1",
            "respostaA": "resposta a",
            "respostaB": "resposta b",
            "respostaC": "resposta c",
            "respostaD": "resposta d",
            "respostaCorreta": "D"
        },
        {
            "pergunta": "Pergunta 2",
            "respostaA": "resposta a",
            "respostaB": "resposta b",
            "respostaC": "resposta c",
            "respostaD": "resposta d",
            "respostaCorreta": "D"
        },
        {
            "pergunta": "Pergunta 3",
            "respostaA": "resposta a",
            "respostaB": "resposta b",
            "respostaC": "resposta c",
            "respostaD": "resposta d",
            "respostaCorreta": "D"
        },
        {
            "pergunta": "Pergunta 5",
            "respostaA": "resposta a",
            "respostaB": "resposta b",
            "respostaC": "resposta c",
            "respostaD": "resposta d",
            "respostaCorreta": "D"
        },
        {
            "pergunta": "Pergunta 6",
            "respostaA": "resposta a",
            "respostaB": "resposta b",
            "respostaC": "resposta c",
            "respostaD": "resposta d",
            "respostaCorreta": "D"
        },
        {
            "pergunta": "Pergunta 7",
            "respostaA": "resposta a",
            "respostaB": "resposta b",
            "respostaC": "resposta c",
            "respostaD": "resposta d",
            "respostaCorreta": "D"
        },
        {
            "pergunta": "Pergunta 8",
            "respostaA": "resposta a",
            "respostaB": "resposta b",
            "respostaC": "resposta c",
            "respostaD": "resposta d",
            "respostaCorreta": "D"
        },
        {
            "pergunta": "Pergunta 9",
            "respostaA": "resposta a",
            "respostaB": "resposta b",
            "respostaC": "resposta c",
            "respostaD": "resposta d",
            "respostaCorreta": "D"
        },
        {
            "pergunta": "Pergunta 10",
            "respostaA": "resposta a",
            "respostaB": "resposta b",
            "respostaC": "resposta c",
            "respostaD": "resposta d",
            "respostaCorreta": "D"
        },
        {
            "pergunta": "Pergunta 11",
            "respostaA": "resposta a",
            "respostaB": "resposta b",
            "respostaC": "resposta c",
            "respostaD": "resposta d",
            "respostaCorreta": "D"
        },
        {
            "pergunta": "Pergunta 12",
            "respostaA": "resposta a",
            "respostaB": "resposta b",
            "respostaC": "resposta c",
            "respostaD": "resposta d",
            "respostaCorreta": "D"
        },
        {
            "pergunta": "Pergunta 13",
            "respostaA": "resposta a",
            "respostaB": "resposta b",
            "respostaC": "resposta c",
            "respostaD": "resposta d",
            "respostaCorreta": "D"
        },
        {
            "pergunta": "Pergunta 14",
            "respostaA": "resposta a",
            "respostaB": "resposta b",
            "respostaC": "resposta c",
            "respostaD": "resposta d",
            "respostaCorreta": "D"
        }
    ]
}